imgstamp/__init__.py
imgstamp/img_stamp.py
imgstamp/text_stamp.py
imgstamp-1.0.dist-info/METADATA
imgstamp-1.0.dist-info/WHEEL
imgstamp-1.0.dist-info/top_level.txt
imgstamp-1.0.dist-info/RECORD
