Metadata-Version: 2.1
Name: imgstamp
Version: 1.0
Summary: lz's utils.
Home-page: https://github.com/yazheng0307/yazheng0307
Author: lz
Author-email: 981638732@qq.com
License: MIT Licence
Keywords: pip,imgstamp
Platform: any
Requires-Dist: tqdm
